apsfacenet/__init__.py
apsfacenet/face_v2.py
apsfacenet-0.0.3.dist-info/METADATA
apsfacenet-0.0.3.dist-info/WHEEL
apsfacenet-0.0.3.dist-info/top_level.txt
apsfacenet-0.0.3.dist-info/RECORD
